{
		"yongl":[
			{
				"name":"zeronum1",
				"type":"text",
				"value":"90"
			},
			{
				"name":"zeronum2",
				"type":"text",
				"value":"100"
			},
			{
				"name":"zeronum3",
				"type":"text",
				"value":"88"
			},
			{
				"name":"zeronum4",
				"type":"text",
				"value":"89"
			},
			{
				"name":"hzzeronum1",
				"type":"text",
				"value":"75"
			},
			{
				"name":"zeronum5",
				"type":"text",
				"value":"92"
			},
			{
				"name":"hzzeronum2",
				"type":"text",
				"value":"68"
			},
			{
				"name":"realgaint1",
				"type":"text",
				"value":"99"
			}
			,
			{
				"name":"realgaint2",
				"type":"text",
				"value":"94"
			}
			,
			{
				"name":"realgaint3",
				"type":"text",
				"value":"100"
			}
			,
			{
				"name":"realgaint4",
				"type":"text",
				"value":"86"
			}
			,
			{
				"name":"realgaint5",
				"type":"text",
				"value":"92"
			},
			{
				"name":"eResult",
				"type":"radio",
				"value":"92"
			}
			
		]

	}